{
  "stats": {
    "health": [
      1200.0,
      1200.0,
      1200.0,
      1200.0,
      1200.0,
      1200.0,
      1200.0,
      1200.0,
      1200.0,
      1200.0,
      1200.0,
      1200.0,
      1200.0,
      1200.0,
      1200.0,
      1200.0,
      1200.0,
      1200.0,
      1200.0,
      1200.0
    ],
    "attack": [
      70.0,
      70.0,
      70.0,
      70.0,
      70.0,
      70.0,
      70.0,
      70.0,
      70.0,
      70.0,
      70.0,
      70.0,
      70.0,
      70.0,
      70.0,
      70.0,
      70.0,
      70.0,
      70.0,
      70.0
    ],
    "spellPower": [
      150.0,
      150.0,
      150.0,
      150.0,
      150.0,
      150.0,
      150.0,
      150.0,
      150.0,
      150.0,
      150.0,
      150.0,
      150.0,
      150.0,
      150.0,
      150.0,
      150.0,
      150.0,
      150.0,
      150.0
    ],
    "attackSpeed": [
      0.67,
      0.75,
      0.82,
      1.0,
      1.1,
      1.2,
      1.3
    ],
    "physicalResist": [
      0.0
    ],
    "magicalResist": [
      0.0
    ],
    "physicalCritChance": [
      0.0
    ],
    "magicalCritChance": [
      0.0
    ],
    "physicalCritDamage": [
      0.0
    ],
    "magicalCritDamage": [
      0.0
    ],
    "moveSpeed": [
      150.0
    ],
    "physHpDrain": [
      0.0
    ],
    "magicHpDrain": [
      0.0
    ],
    "evasion": [
      0.0
    ],
    "rangeId": "goblin_trooper"
  },
  "spellInfo": {
    "mainSpellId": null,
    "secondSpellId": null,
    "thirdSpellId": null
  },
  "viewInfo": {
    "name": "Goblin Trooper",
    "iconId": "hero_icon_goblin_trooper"
  }
}